streamlit_authenticator_sheets/__init__.py
streamlit_authenticator_sheets-0.1.6.dist-info/LICENSE
streamlit_authenticator_sheets-0.1.6.dist-info/METADATA
streamlit_authenticator_sheets-0.1.6.dist-info/WHEEL
streamlit_authenticator_sheets-0.1.6.dist-info/top_level.txt
streamlit_authenticator_sheets-0.1.6.dist-info/RECORD
