Metadata-Version: 2.1
Name: streamlit-authenticator-sheets
Version: 0.1.6
Summary: A secure authentication module to validate user credentials in a Streamlit application using the Google Sheets API and the library of streamlit authenticator.
Home-page: https://github.com/JoseLuisFFDT/streamlit-authenticator-sheets
Author: José Luis Fdez-Figueroa
Author-email: joseluidfft01@gmail.com
Keywords: Python,Streamlit,Authentication,Components
Classifier: Programming Language :: Python :: 3
Classifier: License :: OSI Approved :: MIT License
Classifier: Operating System :: OS Independent
Requires-Python: >=3.6
License-File: LICENSE
Requires-Dist: streamlit >=0.86
Requires-Dist: extra-streamlit-components >=0.1.53
Requires-Dist: bcrypt >=3.1.7
Requires-Dist: PyJWT >=2.3.0
Requires-Dist: PyYAML >=5.3.1
Requires-Dist: google-api-python-client >=2.148.0
Requires-Dist: google-auth-httplib2 >=0.2.0
Requires-Dist: google-auth-oauthlib >=1.2.1
